{
  "project_info": {
    "project_number": "397709827493",
    "project_id": "haifora-v2",
    "storage_bucket": "haifora-v2.firebasestorage.app"
  },
  "client": [
    {
      "client_info": {
        "mobilesdk_app_id": "1:397709827493:android:68f99bff6826f6368ddc4c",
        "android_client_info": {
          "package_name": "com.haifora.app.haifora"
        }
      },
      "oauth_client": [],
      "api_key": [
        {
          "current_key": "AIzaSyBkhBhXmFbM3ymkeO2jamHL0pB6MoCaxVo"
        }
      ],
      "services": {
        "appinvite_service": {
          "other_platform_oauth_client": []
        }
      }
    }
  ],
  "configuration_version": "1"
}